src/__init__.py
src/main.py
src/database/__init__.py
src/metrics/__init__.py
src/metrics/cpu.py
src/metrics/disk.py
src/metrics/memory.py
src/metrics/network.py
src/metrics/system.py
src/utils/__init__.py
src/utils/converter.py
syswatcher-0.1.4.dist-info/METADATA
syswatcher-0.1.4.dist-info/WHEEL
syswatcher-0.1.4.dist-info/entry_points.txt
syswatcher-0.1.4.dist-info/licenses/LICENSE
syswatcher-0.1.4.dist-info/RECORD
